bmi_geotiff/__init__.py
bmi_geotiff/_version.py
bmi_geotiff/bmi.py
bmi_geotiff/io.py
bmi_geotiff-0.4.0.dist-info/licenses/LICENSE.md
bmi_geotiff-0.4.0.dist-info/METADATA
bmi_geotiff-0.4.0.dist-info/WHEEL
bmi_geotiff-0.4.0.dist-info/top_level.txt
bmi_geotiff-0.4.0.dist-info/RECORD
