Metadata-Version: 2.4
Name: bmi-geotiff
Version: 0.4.0
Summary: Access data and metadata in a GeoTIFF file through an API or a BMI
Author-email: Mark Piper <mark.piper@colorado.edu>
License-Expression: MIT
Project-URL: Homepage, https://csdms.colorado.edu
Project-URL: Documentation, https://bmi-geotiff.csdms.io/
Project-URL: Repository, https://github.com/csdms/bmi-geotiff
Project-URL: Changelog, https://github.com/csdms/bmi-geotiff/blob/main/CHANGES.md
Project-URL: Forum, https://forum.csdms.io
Keywords: bmi,geotiff,raster,data
Classifier: Programming Language :: Python :: 3
Classifier: Programming Language :: Python :: 3.12
Classifier: Programming Language :: Python :: 3.13
Classifier: Programming Language :: Python :: 3.14
Classifier: Operating System :: OS Independent
Classifier: Intended Audience :: Developers
Classifier: Intended Audience :: Science/Research
Classifier: Intended Audience :: Education
Classifier: Topic :: Scientific/Engineering
Requires-Python: >=3.10
License-File: LICENSE.md
Requires-Dist: numpy
Requires-Dist: pyyaml
Requires-Dist: xarray
Requires-Dist: rasterio
Requires-Dist: rioxarray
Requires-Dist: bmipy
Provides-Extra: dev
Requires-Dist: nox; extra == "dev"
Provides-Extra: build
Requires-Dist: python-build; extra == "build"
Requires-Dist: twine; extra == "build"
Requires-Dist: zest.releaser; extra == "build"
Provides-Extra: testing
Requires-Dist: pytest; extra == "testing"
Requires-Dist: pytest-cov; extra == "testing"
Requires-Dist: pytest-datadir; extra == "testing"
Requires-Dist: coverage; extra == "testing"
Requires-Dist: coveralls; extra == "testing"
Provides-Extra: docs
Requires-Dist: sphinx; extra == "docs"
Requires-Dist: myst-parser; extra == "docs"
Provides-Extra: examples
Requires-Dist: cartopy; extra == "examples"
Requires-Dist: matplotlib; extra == "examples"
Dynamic: license-file
